{
  "db_name": "PostgreSQL",
  "query": "\n        SELECT\n            n.id,\n            n.contract_id,\n            n.read,\n            n.created_at,\n            n.updated_at,\n            b.name as \"borrower_name!\"\n        FROM lender_contract_chat_message_notifications n\n        INNER JOIN contracts c ON n.contract_id = c.id\n        INNER JOIN borrowers b ON c.borrower_id = b.id\n        WHERE c.lender_id = $1\n        AND ($2 = false OR n.read = false)\n        ORDER BY n.created_at DESC\n        LIMIT $3 OFFSET $4\n        ",
  "describe": {
    "columns": [
      {
        "ordinal": 0,
        "name": "id",
        "type_info": "Uuid"
      },
      {
        "ordinal": 1,
        "name": "contract_id",
        "type_info": "Bpchar"
      },
      {
        "ordinal": 2,
        "name": "read",
        "type_info": "Bool"
      },
      {
        "ordinal": 3,
        "name": "created_at",
        "type_info": "Timestamptz"
      },
      {
        "ordinal": 4,
        "name": "updated_at",
        "type_info": "Timestamptz"
      },
      {
        "ordinal": 5,
        "name": "borrower_name!",
        "type_info": "Varchar"
      }
    ],
    "parameters": {
      "Left": [
        "Bpchar",
        "Bool",
        "Int8",
        "Int8"
      ]
    },
    "nullable": [
      false,
      false,
      false,
      false,
      false,
      false
    ]
  },
  "hash": "a243a482eab13a42c67573657205cd9be4a0a9d27bc3ccd338b52edc700e2aff"
}
